support_sphere/__init__.py
support_sphere/apis/__init__.py
support_sphere/apis/main.py
support_sphere/apis/v1/__init__.py
support_sphere/apis/v1/user_apis.py
support_sphere/models/__init__.py
support_sphere/models/base.py
support_sphere/models/auth/__init__.py
support_sphere/models/auth/user.py
support_sphere/models/enums/__init__.py
support_sphere/models/enums/app_permissions.py
support_sphere/models/enums/app_roles.py
support_sphere/models/enums/operational_status.py
support_sphere/models/enums/priority.py
support_sphere/models/public/__init__.py
support_sphere/models/public/checklist.py
support_sphere/models/public/checklist_step.py
support_sphere/models/public/checklist_steps_order.py
support_sphere/models/public/checklist_steps_state.py
support_sphere/models/public/cluster.py
support_sphere/models/public/frequency.py
support_sphere/models/public/household.py
support_sphere/models/public/operational_event.py
support_sphere/models/public/people.py
support_sphere/models/public/people_group.py
support_sphere/models/public/point_of_interest.py
support_sphere/models/public/resource.py
support_sphere/models/public/resource_cv.py
support_sphere/models/public/resource_subtype_tag.py
support_sphere/models/public/resource_tag.py
support_sphere/models/public/resource_type.py
support_sphere/models/public/role_permission.py
support_sphere/models/public/signup_code.py
support_sphere/models/public/user_captain_cluster.py
support_sphere/models/public/user_checklist.py
support_sphere/models/public/user_profile.py
support_sphere/models/public/user_resource.py
support_sphere/models/public/user_role.py
support_sphere/repositories/__init__.py
support_sphere/repositories/base_repository.py
support_sphere/repositories/auth/__init__.py
support_sphere/repositories/auth/user_repository.py
support_sphere/repositories/public/__init__.py
support_sphere/repositories/public/people_repository.py
support_sphere/repositories/public/user_profile_repository.py
support_sphere_py-0.0.12.dist-info/METADATA
support_sphere_py-0.0.12.dist-info/WHEEL
support_sphere_py-0.0.12.dist-info/entry_points.txt
support_sphere_py-0.0.12.dist-info/licenses/LICENSE
support_sphere_py-0.0.12.dist-info/RECORD
