Metadata-Version: 2.4
Name: support-sphere-py
Version: 0.0.12
Summary: Package for support sphere api service
License: BSD 3-Clause License
License-File: LICENSE
Classifier: Development Status :: 3 - Alpha
Classifier: Intended Audience :: Developers
Classifier: License :: OSI Approved :: BSD License
Classifier: Operating System :: OS Independent
Classifier: Programming Language :: Python :: 3.11
Classifier: Programming Language :: Python :: 3.12
Classifier: Topic :: Scientific/Engineering
Classifier: Topic :: Software Development :: Build Tools
Classifier: Topic :: Software Development :: Libraries :: Python Modules
Requires-Python: >=3.12
Requires-Dist: fastapi[standard]>=0.111.0
Requires-Dist: geoalchemy2>=0.15.2
Requires-Dist: psycopg2-binary<3,>=2.9.9
Requires-Dist: sqlmodel<0.1,>=0.0.21
Requires-Dist: supabase<2.7,>=2.6.0
Requires-Dist: typer
Requires-Dist: uvicorn>=0.30.6
